epistasis/__init__.py
epistasis/__version__.py
epistasis/mapping.py
epistasis/matrix.py
epistasis/matrix_cython.c
epistasis/matrix_cython.cpython-39-darwin.so
epistasis/stats.py
epistasis/utils.py
epistasis/validate.py
epistasis/models/__init__.py
epistasis/models/base.py
epistasis/models/ensemble.py
epistasis/models/pipeline.py
epistasis/models/template.py
epistasis/models/utils.py
epistasis/models/classifiers/__init__.py
epistasis/models/classifiers/base.py
epistasis/models/classifiers/discriminant_analysis.py
epistasis/models/classifiers/gaussian_process.py
epistasis/models/classifiers/gmm.py
epistasis/models/classifiers/logistic.py
epistasis/models/classifiers/template.py
epistasis/models/classifiers/tests/__init__.py
epistasis/models/classifiers/tests/test_classifiers.py
epistasis/models/linear/__init__.py
epistasis/models/linear/elastic_net.py
epistasis/models/linear/lasso.py
epistasis/models/linear/ordinary.py
epistasis/models/linear/ridge.py
epistasis/models/linear/tests/__init__.py
epistasis/models/linear/tests/test_lasso.py
epistasis/models/linear/tests/test_ordinary.py
epistasis/models/linear/tests/test_ridge.py
epistasis/models/nonlinear/__init__.py
epistasis/models/nonlinear/minimizer.py
epistasis/models/nonlinear/ordinary.py
epistasis/models/nonlinear/power.py
epistasis/models/nonlinear/spline.py
epistasis/models/nonlinear/tests/__init__.py
epistasis/models/nonlinear/tests/test_ordinary.py
epistasis/models/tests/__init__.py
epistasis/models/tests/test_utils.py
epistasis/pyplot/__init__.py
epistasis/pyplot/coefs.py
epistasis/pyplot/nonlinear.py
epistasis/sampling/__init__.py
epistasis/sampling/bayesian.py
epistasis/sampling/tests/__init__.py
epistasis/sampling/tests/test_bayesian.py
epistasis/simulate/__init__.py
epistasis/simulate/base.py
epistasis/simulate/linear.py
epistasis/simulate/mapping.py
epistasis/simulate/power.py
epistasis/simulate/tests/__init__.py
epistasis/simulate/tests/test_base.py
epistasis/simulate/tests/test_linear.py
epistasis-0.7.5.dist-info/METADATA
epistasis-0.7.5.dist-info/WHEEL
epistasis-0.7.5.dist-info/top_level.txt
epistasis-0.7.5.dist-info/RECORD
