Metadata-Version: 2.1
Name: epistasis
Version: 0.7.5
Summary: A Python API for estimating statistical high-order epistasis in genotype-phenotype maps.
Home-page: https://github.com/harmslab/epistasis
Author: Zachary R. Sailer
Author-email: zachsailer@gmail.com
License: UNLICENSE
Keywords: epistasis high-order genetics genotype-phenotype-maps
Platform: UNKNOWN
Classifier: Development Status :: 3 - Alpha
Classifier: Intended Audience :: Science/Research
Classifier: Programming Language :: Python :: 3.4
Classifier: Programming Language :: Python :: 3.5
Classifier: Programming Language :: Python :: 3.6
Requires-Python: >=3.3.0
Requires-Dist: cython
Requires-Dist: numpy (>=1.15.2)
Requires-Dist: pandas (>=0.24.2)
Requires-Dist: scikit-learn (>=0.20.0)
Requires-Dist: scipy (>=1.1.0)
Requires-Dist: emcee (>=2.2.1)
Requires-Dist: lmfit (>=0.9.11)
Requires-Dist: matplotlib (>=3.0.0)
Requires-Dist: gpmap (>=0.6.0)
Provides-Extra: test
Requires-Dist: pytest ; extra == 'test'
